pytro2th/__init__.py
pytro2th/_version.py
pytro2th/buildparam.py
pytro2th/buildthconfig.py
pytro2th/command_line.py
pytro2th/datathwritetools.py
pytro2th/tro2th.py
pytro2th/vtopotools.py
pytro2th/tests/Test.py
pytro2th/tests/__init__.py
pytherion-1.2.0.dist-info/LICENCE.txt
pytherion-1.2.0.dist-info/METADATA
pytherion-1.2.0.dist-info/WHEEL
pytherion-1.2.0.dist-info/top_level.txt
pytherion-1.2.0.dist-info/RECORD
