Metadata-Version: 2.1
Name: pytherion
Version: 1.2.0
Summary: Module that provides tools for manage data transformations for the software Therion
Author: Xavier Robert
Author-email: xavier.Robert@univ-grenoble-alpes.fr
License: GPL-V3.0
License-File: LICENCE.txt
